py_models_parser/__init__.py
py_models_parser/cli.py
py_models_parser/core.py
py_models_parser/grammar.py
py_models_parser/parsers/openapi.py
py_models_parser/parsers/pydal.py
py_models_parser/types.py
py_models_parser/utils.py
py_models_parser/visitor.py
py_models_parser-1.0.0.dist-info/METADATA
py_models_parser-1.0.0.dist-info/WHEEL
py_models_parser-1.0.0.dist-info/entry_points.txt
py_models_parser-1.0.0.dist-info/licenses/LICENSE
py_models_parser-1.0.0.dist-info/RECORD
