Metadata-Version: 2.4
Name: py-models-parser
Version: 1.0.0
Summary: Parser for Different Python Models (Pydantic, Enums, ORMs: Tortoise, SqlAlchemy, GinoORM, PonyORM, Pydal tables) to extract information about columns(attrs), model, table args,etc in one format.
License: MIT
License-File: LICENSE
Author: Iuliia Volkova
Author-email: xnuinside@gmail.com
Requires-Python: >=3.9,<4.0
Classifier: License :: OSI Approved :: MIT License
Classifier: Programming Language :: PL/SQL
Classifier: Programming Language :: Python :: 3
Classifier: Programming Language :: Python :: 3.9
Classifier: Programming Language :: Python :: 3.10
Classifier: Programming Language :: Python :: 3.11
Classifier: Programming Language :: Python :: 3.12
Classifier: Programming Language :: Python :: 3.13
Classifier: Programming Language :: Python :: 3.14
Classifier: Programming Language :: SQL
Classifier: Topic :: Software Development
Classifier: Topic :: Software Development :: Code Generators
Classifier: Topic :: Software Development :: Libraries
Classifier: Topic :: Software Development :: Libraries :: Python Modules
Classifier: Topic :: Utilities
Requires-Dist: parsimonious (>=0.10.0,<0.11.0)
Requires-Dist: pyyaml (>=6.0.1,<7.0.0)
Project-URL: Homepage, https://github.com/xnuinside/py-models-parser
Project-URL: Repository, https://github.com/xnuinside/py-models-parser
